pwutil/__init__.py
pwutil/badpw.py
pwutil-0.3.0.dist-info/LICENSE
pwutil-0.3.0.dist-info/METADATA
pwutil-0.3.0.dist-info/WHEEL
pwutil-0.3.0.dist-info/top_level.txt
pwutil-0.3.0.dist-info/RECORD
